{
    "name": "makerbit-touch-jacdac",
    "version": "1.2.19",
    "dependencies": {
        "core": "*",
        "radio": "*",
        "microphone": "*",
        "MakerBit-Touch": "github:pelikhan/pxt-makerbit-touch",
        "jacdac": "github:microsoft/pxt-jacdac#v0.10.14",
        "jacdac-button": "github:microsoft/pxt-jacdac/button#v0.10.14"
    },
    "files": [
        "main.ts",
        "README.md"
    ],
    "testFiles": [
        "test.ts"
    ],
    "targetVersions": {
        "target": "4.1.27",
        "targetId": "microbit"
    },
    "supportedTargets": [
        "microbit"
    ],
    "preferredEditor": "tsprj"
}
